kotlin_cli-0.1.1.dist-info/licenses/LICENSE
mycommand/__init__.py
mycommand/cli.py
kotlin_cli-0.1.1.dist-info/METADATA
kotlin_cli-0.1.1.dist-info/WHEEL
kotlin_cli-0.1.1.dist-info/entry_points.txt
kotlin_cli-0.1.1.dist-info/top_level.txt
kotlin_cli-0.1.1.dist-info/RECORD
